pymagnitudelight/__init__.py
pymagnitudelight/converter.py
pymagnitudelight/converter_shared.py
pymagnitudelight/framework/__init__.py
pymagnitudelight/framework/repoze/__init__.py
pymagnitudelight/framework/repoze/lru/__init__.py
pymagnitudelight/framework/repoze/lru/tests.py
pymagnitude_light-0.1.147.dist-info/LICENSE.txt
pymagnitude_light-0.1.147.dist-info/METADATA
pymagnitude_light-0.1.147.dist-info/WHEEL
pymagnitude_light-0.1.147.dist-info/top_level.txt
pymagnitude_light-0.1.147.dist-info/RECORD
