Metadata-Version: 2.1
Name: pymagnitude-light
Version: 0.1.147
Summary: Magnitude fork that only supports Word2Vec, GloVe and fastText embeddings
Home-page: https://github.com/davebulaval/magnitude-light
License: MIT
Platform: UNKNOWN
Requires-Dist: fasteners (>=0.14.1)
Requires-Dist: lz4 (>=1.0.0)
Requires-Dist: numpy (>=1.14.0)
Requires-Dist: xxhash (>=1.0.1)
